mypy_structured_data/__init__.py
mypy_structured_data-0.1.1.dist-info/AUTHORS.rst
mypy_structured_data-0.1.1.dist-info/LICENSE
mypy_structured_data-0.1.1.dist-info/METADATA
mypy_structured_data-0.1.1.dist-info/WHEEL
mypy_structured_data-0.1.1.dist-info/top_level.txt
mypy_structured_data-0.1.1.dist-info/RECORD
